{
  "target_id": "MD-176",
  "capability_id": "md.strategy.corporate-strategy-portfolio-and-capital-allocation",
  "evidence_lane": "factual",
  "risk_level": "high",
  "expected_output": "results/corporate_strategy_portfolio_and_capital_allocation/corporate_strategy_portfolio_and_capital_allocation_result.md",
  "fixture_id": "MD-176-healthy",
  "tier": "healthy",
  "input_conditions": [
    "current authoritative evidence",
    "explicit scope and authority",
    "valid required inputs"
  ],
  "expected": [
    "complete declared artifact",
    "schema-valid supporting artifacts",
    "verification and residual record"
  ],
  "prohibited": [
    "fabricated evidence",
    "silent external action"
  ],
  "execution_status": "definition_only_not_model_executed"
}
